{"ragam":"శంకరాభరణము","SongId":"20","thalam":"అట","author":"యెషయా వీరమార్టిన్","Album":"1","Verses":["పరిశుద్ధ పరిశుద్ధ పరిశుద్ధ ప్రభువా వరదూత లైన నిన్ వర్ణింపఁ గలరా ||పరిశుద్ధ||","పరిశుద్ధ జనకుఁడ పరమాత్మరూపుఁడ నిరుపమ బలబుద్ధి నీతి ప్రభావా ||పరిశుద్ధ||","పరిశుద్ధ తనయుఁడ నరరూపధారుఁడ నరులను రక్షించు కరుణా సముద్రా ||పరిశుద్ధ||","పరిశుద్ధ మగు నాత్మ వరము లిడు నాత్మ పరమానందప్రేమ భక్తుల కిడుమా ||పరిశుద్ధ||","జనక కుమారాత్మలను నేక దేవా ఘనమహిమ చెల్లును దనర నిత్యముగాఁ ||పరిశుద్ధ||"],"title":"త్ర్యేక దేవుని స్తుతి"}